open_webdriver/__init__.py
open_webdriver/demo_app.py
open_webdriver/download_chromium2.py
open_webdriver/main.py
open_webdriver/path.py
open_webdriver/version.py
open_webdriver/archive/download_chromium.py
open_webdriver/tests/__init__.py
open_webdriver/tests/nuitka/__init__.py
open_webdriver/tests/nuitka/test_binary_build.py
open_webdriver/tests/unit/__init__.py
open_webdriver/tests/unit/cmd_test.py
open_webdriver/tests/unit/test_concurrent_webdriver.py
open_webdriver/tests/unit/test_osenv.py
open_webdriver/tests/unit/test_webdriver.py
open_webdriver-1.6.9.dist-info/licenses/LICENSE
open_webdriver-1.6.9.dist-info/METADATA
open_webdriver-1.6.9.dist-info/WHEEL
open_webdriver-1.6.9.dist-info/entry_points.txt
open_webdriver-1.6.9.dist-info/top_level.txt
open_webdriver-1.6.9.dist-info/RECORD
