Metadata-Version: 2.4
Name: open_webdriver
Version: 1.6.9
Summary: Easiest zero-config selenium webdriver for Python
Home-page: https://github.com/zackees/open-webdriver
Maintainer: Zachary Vorhies
License: BSD 3-Clause License
Keywords: web driver easy setup
Classifier: Programming Language :: Python :: 3
Requires-Python: >=3.10
License-File: LICENSE
Requires-Dist: selenium==4.30.0
Requires-Dist: download
Requires-Dist: filelock
Requires-Dist: py7zr==0.20.2
Requires-Dist: certifi
Requires-Dist: six
Requires-Dist: httpx
Dynamic: home-page
Dynamic: license-file
Dynamic: maintainer
